{
  "date": "20260403",
  "total_races": 5,
  "hits": 1,
  "total_bet": 3600,
  "total_payout": 3220,
  "roi": 89.44444444444444,
  "look_count": 0,
  "results": [
    {
      "venue": "福岡",
      "race_no": 6,
      "actual": "1-2-5",
      "kimarite": "抜き",
      "payout_odds": 1610,
      "hit": true,
      "bet_amount": 600,
      "win_amount": 3220,
      "race_type": "本命崩れ"
    },
    {
      "venue": "福岡",
      "race_no": 7,
      "actual": "3-2-4",
      "kimarite": "まくり",
      "payout_odds": 1020,
      "hit": false,
      "bet_amount": 700,
      "win_amount": 0,
      "race_type": "本命崩れ"
    },
    {
      "venue": "福岡",
      "race_no": 8,
      "actual": "5-4-2",
      "kimarite": "まくり差し",
      "payout_odds": 10080,
      "hit": false,
      "bet_amount": 800,
      "win_amount": 0,
      "race_type": "本命崩れ"
    },
    {
      "venue": "桐生",
      "race_no": 4,
      "actual": "0-0-0",
      "kimarite": "",
      "payout_odds": 0,
      "hit": false,
      "bet_amount": 700,
      "win_amount": 0,
      "race_type": "本命崩れ"
    },
    {
      "venue": "桐生",
      "race_no": 5,
      "actual": "0-0-0",
      "kimarite": "",
      "payout_odds": 0,
      "hit": false,
      "bet_amount": 800,
      "win_amount": 0,
      "race_type": "本命崩れ"
    }
  ]
}